{"name":"TORNEO INDEPENDENCIA IXTEPEC OAXACA","number_of_rounds":5,"players":[{"federation":"PRI","flags":"","gender":"M","id":"","name":"ALONSO CASTILLO EIDEN","official_rating":false,"pairing_number":1,"rating":0},{"federation":"PRE","flags":"","gender":"M","id":"","name":"ALONSO CASTILLO EMMANUEL","official_rating":false,"pairing_number":2,"rating":0},{"federation":"PRI","flags":"","gender":"M","id":"","name":"ARAGON GUZMAN EMILIANO","official_rating":false,"pairing_number":3,"rating":0},{"federation":"PRI","flags":"","gender":"M","id":"","name":"ARAGON GUZMAN SEBASTIAN","official_rating":false,"pairing_number":4,"rating":0},{"federation":"PRE","flags":"","gender":"M","id":"","name":"AVILA TOLEDO ALEJANDRO","official_rating":false,"pairing_number":5,"rating":0},{"federation":"PRE","flags":"","gender":"M","id":"","name":"BARTOLO ESTEVA LUIS","official_rating":false,"pairing_number":6,"rating":0},{"federation":"PRI","flags":"","gender":"M","id":"","name":"CALVO ALVARADO EMILIO DIDI","official_rating":false,"pairing_number":7,"rating":0},{"federation":"PRI","flags":"","gender":"M","id":"","name":"CARRASCO PALOMEC ARATH JOS","official_rating":false,"pairing_number":8,"rating":0},{"federation":"PRE","flags":"","gender":"M","id":"","name":"CORONA SOTO CARLOS DANIEL","official_rating":false,"pairing_number":9,"rating":0},{"federation":"PRE","flags":"","gender":"M","id":"","name":"CORTES SANCHEZ JHONATAN YA","official_rating":false,"pairing_number":10,"rating":0},{"federation":"SEC","flags":"","gender":"F","id":"","name":"CORTEZ RUIZ GIOVANA SICARU","official_rating":false,"pairing_number":11,"rating":0},{"federation":"PRE","flags":"","gender":"M","id":"","name":"CORTEZ RUIZ LUIS ARTURO","official_rating":false,"pairing_number":12,"rating":0},{"federation":"PRI","flags":"","gender":"F","id":"","name":"CRUZ GALVAN MELYZA","official_rating":false,"pairing_number":13,"rating":0},{"federation":"PRI","flags":"","gender":"F","id":"","name":"CRUZ GALVAN RENATA","official_rating":false,"pairing_number":14,"rating":0},{"federation":"PRE","flags":"","gender":"M","id":"","name":"DIAZ ZAVALA AXEL RICARDO","official_rating":false,"pairing_number":15,"rating":0},{"federation":"PRI","flags":"","gender":"M","id":"","name":"FUENTES MIJANGOS GERARDO","official_rating":false,"pairing_number":16,"rating":0},{"federation":"SEC","flags":"","gender":"M","id":"","name":"GOMEZ JARQUIN ABDIEL","official_rating":false,"pairing_number":17,"rating":0},{"federation":"SEC","flags":"","gender":"M","id":"","name":"GOMEZ VENEGAS JAVIN MAXIMI","official_rating":false,"pairing_number":18,"rating":0},{"federation":"PRI","flags":"","gender":"M","id":"","name":"GONZALEZ PACHECO ABDIEL YU","official_rating":false,"pairing_number":19,"rating":0},{"federation":"SEC","flags":"","gender":"F","id":"","name":"GONZALEZ PASCUAL CECILIA S","official_rating":false,"pairing_number":20,"rating":0},{"federation":"PRE","flags":"","gender":"F","id":"","name":"GONZALEZ PASCUAL EMILY MAR","official_rating":false,"pairing_number":21,"rating":0},{"federation":"PRI","flags":"","gender":"M","id":"","name":"GUERRA ZAMORA CHRISTOPHER","official_rating":false,"pairing_number":22,"rating":0},{"federation":"PRI","flags":"","gender":"M","id":"","name":"GUZMAN CASTRO GAMALIEL","official_rating":false,"pairing_number":23,"rating":0},{"federation":"PRI","flags":"","gender":"M","id":"","name":"GUZMAN CASTRO WILBERT BENJ","official_rating":false,"pairing_number":24,"rating":0},{"federation":"PRE","flags":"","gender":"M","id":"","name":"HENANDEZ HERNANDEZ ALEXIS","official_rating":false,"pairing_number":25,"rating":0},{"federation":"PRE","flags":"","gender":"M","id":"","name":"HERNANDEZ HERNANDEZ WILLIA","official_rating":false,"pairing_number":26,"rating":0},{"federation":"PRI","flags":"","gender":"F","id":"","name":"HISCOCK PEREZ ISABELLA","official_rating":false,"pairing_number":27,"rating":0},{"federation":"PRI","flags":"","gender":"M","id":"","name":"JIMENEZ ENRIQUEZ SEVERO XA","official_rating":false,"pairing_number":28,"rating":0},{"federation":"PRI","flags":"","gender":"M","id":"","name":"JIMENEZ TOLEDO AXEL","official_rating":false,"pairing_number":29,"rating":0},{"federation":"PRE","flags":"","gender":"M","id":"","name":"LOPEZ SOLORZANO ANGEL CALE","official_rating":false,"pairing_number":30,"rating":0},{"federation":"SEC","flags":"","gender":"M","id":"","name":"LOPEZ VALDIVIEZO ANGEL FAB","official_rating":false,"pairing_number":31,"rating":0},{"federation":"PRI","flags":"","gender":"F","id":"","name":"MORALES RASGADO BIANII","official_rating":false,"pairing_number":32,"rating":0},{"federation":"PRI","flags":"","gender":"F","id":"","name":"MOYA JIMENEZ AMAYA","official_rating":false,"pairing_number":33,"rating":0},{"federation":"PRI","flags":"","gender":"M","id":"","name":"OLIVERA GUZMAN DAVID","official_rating":false,"pairing_number":34,"rating":0},{"federation":"SEC","flags":"","gender":"F","id":"","name":"OROZCO GOMEZ XIMENA","official_rating":false,"pairing_number":35,"rating":0},{"federation":"SEC","flags":"","gender":"M","id":"","name":"PASCUAL MANUEL JOSUE GERMA","official_rating":false,"pairing_number":36,"rating":0},{"federation":"PRI","flags":"","gender":"F","id":"","name":"PEREZ CORDOVA ZAZUEIRA LIL","official_rating":false,"pairing_number":37,"rating":0},{"federation":"PRI","flags":"","gender":"M","id":"","name":"PEREZ SANCHEZ RICARDO BALA","official_rating":false,"pairing_number":38,"rating":0},{"federation":"SEC","flags":"","gender":"F","id":"","name":"PINEDA ANTONIO YERINE DEL","official_rating":false,"pairing_number":39,"rating":0},{"federation":"SEC","flags":"","gender":"F","id":"","name":"PINEDA ANTONIO YUNERI DEL","official_rating":false,"pairing_number":40,"rating":0},{"federation":"PRI","flags":"","gender":"F","id":"","name":"RASGADO ORTEGA SHEILA","official_rating":false,"pairing_number":41,"rating":0},{"federation":"SEC","flags":"","gender":"F","id":"","name":"ROSADO ZARATE MARIA JOSÉ","official_rating":false,"pairing_number":42,"rating":0},{"federation":"PRI","flags":"","gender":"M","id":"","name":"RUIZ HERNANDEZ OLIVER","official_rating":false,"pairing_number":43,"rating":0},{"federation":"PRI","flags":"","gender":"M","id":"","name":"SANCHEZ BLAS FRANCO LAEL","official_rating":false,"pairing_number":44,"rating":0},{"federation":"PRI","flags":"","gender":"M","id":"","name":"SANTIAGO ARELLANO IKER EST","official_rating":false,"pairing_number":45,"rating":0},{"federation":"SEC","flags":"","gender":"M","id":"","name":"SANTIAGO OROZCO MATIAS GER","official_rating":false,"pairing_number":46,"rating":0},{"federation":"PRI","flags":"","gender":"F","id":"","name":"SATURNINO HERNANDEZ FERNAN","official_rating":false,"pairing_number":47,"rating":0},{"federation":"SEC","flags":"","gender":"M","id":"","name":"SOLIS JIMENEZ HELSIS GERAR","official_rating":false,"pairing_number":48,"rating":0},{"federation":"SEC","flags":"","gender":"M","id":"","name":"TOLEDO GOMEZ ZAHIR ISRAEL","official_rating":false,"pairing_number":49,"rating":0},{"federation":"PRE","flags":"","gender":"F","id":"","name":"VARGAS MOYA IVANNA YARAZET","official_rating":false,"pairing_number":50,"rating":0},{"federation":"PRI","flags":"","gender":"F","id":"","name":"VASQUEZ LOPEZ BARBARA GITZ","official_rating":false,"pairing_number":51,"rating":0},{"federation":"SEC","flags":"","gender":"F","id":"","name":"VAZQUEZ GUZMAN FERNANDA AZ","official_rating":false,"pairing_number":52,"rating":0},{"federation":"SEC","flags":"","gender":"M","id":"","name":"VAZQUEZ LOPEZ CALEB NICOLA","official_rating":false,"pairing_number":53,"rating":0},{"federation":"PRI","flags":"","gender":"F","id":"","name":"VAZQUEZ LOPEZ LUIS ISAIAS","official_rating":false,"pairing_number":54,"rating":0},{"federation":"SEC","flags":"","gender":"F","id":"","name":"VICENTE SANCHEZ LILIA ITZE","official_rating":false,"pairing_number":55,"rating":0},{"federation":"PRI","flags":"","gender":"M","id":"","name":"VICENTE SANCHEZ RAFAEL","official_rating":false,"pairing_number":56,"rating":0},{"federation":"PRE","flags":"","gender":"M","id":"","name":"VICTORIANO JIMENEZ ERICK","official_rating":false,"pairing_number":57,"rating":0},{"federation":"SEC","flags":"","gender":"M","id":"","name":"VILLALOBOS GOMEZ GILBERTO","official_rating":false,"pairing_number":58,"rating":0},{"federation":"SEC","flags":"","gender":"M","id":"","name":"VILLALOBOS PINEDA KEVIN ZA","official_rating":false,"pairing_number":59,"rating":0}],"rounds":[{"byes":[{"pairing_allocated":true,"player":59,"score":1.0}],"date":"2025-09-13","number":1,"pairings":[{"black":1,"black_points":1.0,"table":1,"white":30,"white_points":0.0},{"black":31,"black_points":0.0,"table":2,"white":2,"white_points":1.0},{"black":3,"black_points":1.0,"table":3,"white":32,"white_points":0.0},{"black":33,"black_points":1.0,"table":4,"white":4,"white_points":0.0},{"black":5,"black_points":1.0,"table":5,"white":34,"white_points":0.0},{"black":35,"black_points":1.0,"table":6,"white":6,"white_points":0.0},{"black":7,"black_points":0.0,"table":7,"white":36,"white_points":1.0},{"black":37,"black_points":1.0,"table":8,"white":8,"white_points":0.0},{"black":9,"black_points":0.0,"table":9,"white":38,"white_points":1.0},{"black":39,"black_points":1.0,"table":10,"white":10,"white_points":0.0},{"black":11,"black_points":0.0,"table":11,"white":40,"white_points":1.0},{"black":41,"black_points":0.0,"table":12,"white":12,"white_points":1.0},{"black":13,"black_points":1.0,"table":13,"white":42,"white_points":0.0},{"black":43,"black_points":1.0,"table":14,"white":14,"white_points":0.0},{"black":15,"black_points":1.0,"table":15,"white":44,"white_points":0.0},{"black":45,"black_points":1.0,"table":16,"white":16,"white_points":0.0},{"black":17,"black_points":1.0,"table":17,"white":46,"white_points":0.0},{"black":47,"black_points":0.0,"table":18,"white":18,"white_points":1.0},{"black":19,"black_points":0.0,"table":19,"white":48,"white_points":1.0},{"black":49,"black_points":0.0,"table":20,"white":20,"white_points":1.0},{"black":21,"black_points":1.0,"table":21,"white":50,"white_points":0.0},{"black":51,"black_points":0.0,"table":22,"white":22,"white_points":1.0},{"black":23,"black_points":0.0,"table":23,"white":52,"white_points":1.0},{"black":53,"black_points":1.0,"table":24,"white":24,"white_points":0.0},{"black":25,"black_points":0.0,"table":25,"white":54,"white_points":1.0},{"black":55,"black_points":1.0,"table":26,"white":26,"white_points":0.0},{"black":27,"black_points":0.0,"table":27,"white":56,"white_points":1.0},{"black":57,"black_points":1.0,"table":28,"white":28,"white_points":0.0},{"black":29,"black_points":1.0,"table":29,"white":58,"white_points":0.0}],"ranking":[{"average_rating_cut":1000.0,"buchholz":0.0,"buchholz_cut":0.0,"color_balance":-1,"mutual_result_top":0.0,"player":1,"progressive_score":1.0,"rank":1,"score":1.0,"sonneborn_berger":0.0,"tpr":0,"tpr_mixed":0},{"average_rating_cut":1000.0,"buchholz":0.0,"buchholz_cut":0.0,"color_balance":1,"mutual_result_top":0.0,"player":2,"progressive_score":1.0,"rank":2,"score":1.0,"sonneborn_berger":0.0,"tpr":0,"tpr_mixed":0},{"average_rating_cut":1000.0,"buchholz":0.0,"buchholz_cut":0.0,"color_balance":-1,"mutual_result_top":0.0,"player":3,"progressive_score":1.0,"rank":3,"score":1.0,"sonneborn_berger":0.0,"tpr":0,"tpr_mixed":0},{"average_rating_cut":1000.0,"buchholz":0.0,"buchholz_cut":0.0,"color_balance":-1,"mutual_result_top":0.0,"player":5,"progressive_score":1.0,"rank":4,"score":1.0,"sonneborn_berger":0.0,"tpr":0,"tpr_mixed":0},{"average_rating_cut":1000.0,"buchholz":0.0,"buchholz_cut":0.0,"color_balance":1,"mutual_result_top":0.0,"player":12,"progressive_score":1.0,"rank":5,"score":1.0,"sonneborn_berger":0.0,"tpr":0,"tpr_mixed":0},{"average_rating_cut":1000.0,"buchholz":0.0,"buchholz_cut":0.0,"color_balance":-1,"mutual_result_top":0.0,"player":13,"progressive_score":1.0,"rank":6,"score":1.0,"sonneborn_berger":0.0,"tpr":0,"tpr_mixed":0},{"average_rating_cut":1000.0,"buchholz":0.0,"buchholz_cut":0.0,"color_balance":-1,"mutual_result_top":0.0,"player":15,"progressive_score":1.0,"rank":7,"score":1.0,"sonneborn_berger":0.0,"tpr":0,"tpr_mixed":0},{"average_rating_cut":1000.0,"buchholz":0.0,"buchholz_cut":0.0,"color_balance":-1,"mutual_result_top":0.0,"player":17,"progressive_score":1.0,"rank":8,"score":1.0,"sonneborn_berger":0.0,"tpr":0,"tpr_mixed":0},{"average_rating_cut":1000.0,"buchholz":0.0,"buchholz_cut":0.0,"color_balance":1,"mutual_result_top":0.0,"player":18,"progressive_score":1.0,"rank":9,"score":1.0,"sonneborn_berger":0.0,"tpr":0,"tpr_mixed":0},{"average_rating_cut":1000.0,"buchholz":0.0,"buchholz_cut":0.0,"color_balance":1,"mutual_result_top":0.0,"player":20,"progressive_score":1.0,"rank":10,"score":1.0,"sonneborn_berger":0.0,"tpr":0,"tpr_mixed":0},{"average_rating_cut":1000.0,"buchholz":0.0,"buchholz_cut":0.0,"color_balance":-1,"mutual_result_top":0.0,"player":21,"progressive_score":1.0,"rank":11,"score":1.0,"sonneborn_berger":0.0,"tpr":0,"tpr_mixed":0},{"average_rating_cut":1000.0,"buchholz":0.0,"buchholz_cut":0.0,"color_balance":1,"mutual_result_top":0.0,"player":22,"progressive_score":1.0,"rank":12,"score":1.0,"sonneborn_berger":0.0,"tpr":0,"tpr_mixed":0},{"average_rating_cut":1000.0,"buchholz":0.0,"buchholz_cut":0.0,"color_balance":-1,"mutual_result_top":0.0,"player":29,"progressive_score":1.0,"rank":13,"score":1.0,"sonneborn_berger":0.0,"tpr":0,"tpr_mixed":0},{"average_rating_cut":1000.0,"buchholz":0.0,"buchholz_cut":0.0,"color_balance":-1,"mutual_result_top":0.0,"player":33,"progressive_score":1.0,"rank":14,"score":1.0,"sonneborn_berger":0.0,"tpr":0,"tpr_mixed":0},{"average_rating_cut":1000.0,"buchholz":0.0,"buchholz_cut":0.0,"color_balance":-1,"mutual_result_top":0.0,"player":35,"progressive_score":1.0,"rank":15,"score":1.0,"sonneborn_berger":0.0,"tpr":0,"tpr_mixed":0},{"average_rating_cut":1000.0,"buchholz":0.0,"buchholz_cut":0.0,"color_balance":1,"mutual_result_top":0.0,"player":36,"progressive_score":1.0,"rank":16,"score":1.0,"sonneborn_berger":0.0,"tpr":0,"tpr_mixed":0},{"average_rating_cut":1000.0,"buchholz":0.0,"buchholz_cut":0.0,"color_balance":-1,"mutual_result_top":0.0,"player":37,"progressive_score":1.0,"rank":17,"score":1.0,"sonneborn_berger":0.0,"tpr":0,"tpr_mixed":0},{"average_rating_cut":1000.0,"buchholz":0.0,"buchholz_cut":0.0,"color_balance":1,"mutual_result_top":0.0,"player":38,"progressive_score":1.0,"rank":18,"score":1.0,"sonneborn_berger":0.0,"tpr":0,"tpr_mixed":0},{"average_rating_cut":1000.0,"buchholz":0.0,"buchholz_cut":0.0,"color_balance":-1,"mutual_result_top":0.0,"player":39,"progressive_score":1.0,"rank":19,"score":1.0,"sonneborn_berger":0.0,"tpr":0,"tpr_mixed":0},{"average_rating_cut":1000.0,"buchholz":0.0,"buchholz_cut":0.0,"color_balance":1,"mutual_result_top":0.0,"player":40,"progressive_score":1.0,"rank":20,"score":1.0,"sonneborn_berger":0.0,"tpr":0,"tpr_mixed":0},{"average_rating_cut":1000.0,"buchholz":0.0,"buchholz_cut":0.0,"color_balance":-1,"mutual_result_top":0.0,"player":43,"progressive_score":1.0,"rank":21,"score":1.0,"sonneborn_berger":0.0,"tpr":0,"tpr_mixed":0},{"average_rating_cut":1000.0,"buchholz":0.0,"buchholz_cut":0.0,"color_balance":-1,"mutual_result_top":0.0,"player":45,"progressive_score":1.0,"rank":22,"score":1.0,"sonneborn_berger":0.0,"tpr":0,"tpr_mixed":0},{"average_rating_cut":1000.0,"buchholz":0.0,"buchholz_cut":0.0,"color_balance":1,"mutual_result_top":0.0,"player":48,"progressive_score":1.0,"rank":23,"score":1.0,"sonneborn_berger":0.0,"tpr":0,"tpr_mixed":0},{"average_rating_cut":1000.0,"buchholz":0.0,"buchholz_cut":0.0,"color_balance":1,"mutual_result_top":0.0,"player":52,"progressive_score":1.0,"rank":24,"score":1.0,"sonneborn_berger":0.0,"tpr":0,"tpr_mixed":0},{"average_rating_cut":1000.0,"buchholz":0.0,"buchholz_cut":0.0,"color_balance":-1,"mutual_result_top":0.0,"player":53,"progressive_score":1.0,"rank":25,"score":1.0,"sonneborn_berger":0.0,"tpr":0,"tpr_mixed":0},{"average_rating_cut":1000.0,"buchholz":0.0,"buchholz_cut":0.0,"color_balance":1,"mutual_result_top":0.0,"player":54,"progressive_score":1.0,"rank":26,"score":1.0,"sonneborn_berger":0.0,"tpr":0,"tpr_mixed":0},{"average_rating_cut":1000.0,"buchholz":0.0,"buchholz_cut":0.0,"color_balance":-1,"mutual_result_top":0.0,"player":55,"progressive_score":1.0,"rank":27,"score":1.0,"sonneborn_berger":0.0,"tpr":0,"tpr_mixed":0},{"average_rating_cut":1000.0,"buchholz":0.0,"buchholz_cut":0.0,"color_balance":1,"mutual_result_top":0.0,"player":56,"progressive_score":1.0,"rank":28,"score":1.0,"sonneborn_berger":0.0,"tpr":0,"tpr_mixed":0},{"average_rating_cut":1000.0,"buchholz":0.0,"buchholz_cut":0.0,"color_balance":-1,"mutual_result_top":0.0,"player":57,"progressive_score":1.0,"rank":29,"score":1.0,"sonneborn_berger":0.0,"tpr":0,"tpr_mixed":0},{"average_rating_cut":0.0,"buchholz":0.0,"buchholz_cut":0.0,"color_balance":1,"mutual_result_top":0.0,"player":59,"progressive_score":1.0,"rank":30,"score":1.0,"sonneborn_berger":0.0,"tpr":0,"tpr_mixed":0},{"average_rating_cut":1000.0,"buchholz":1.0,"buchholz_cut":1.0,"color_balance":1,"player":4,"progressive_score":0.0,"rank":31,"score":0.0,"sonneborn_berger":0.0,"tpr":0,"tpr_mixed":0},{"average_rating_cut":1000.0,"buchholz":1.0,"buchholz_cut":1.0,"color_balance":1,"player":6,"progressive_score":0.0,"rank":32,"score":0.0,"sonneborn_berger":0.0,"tpr":0,"tpr_mixed":0},{"average_rating_cut":1000.0,"buchholz":1.0,"buchholz_cut":1.0,"color_balance":-1,"player":7,"progressive_score":0.0,"rank":33,"score":0.0,"sonneborn_berger":0.0,"tpr":0,"tpr_mixed":0},{"average_rating_cut":1000.0,"buchholz":1.0,"buchholz_cut":1.0,"color_balance":1,"player":8,"progressive_score":0.0,"rank":34,"score":0.0,"sonneborn_berger":0.0,"tpr":0,"tpr_mixed":0},{"average_rating_cut":1000.0,"buchholz":1.0,"buchholz_cut":1.0,"color_balance":-1,"player":9,"progressive_score":0.0,"rank":35,"score":0.0,"sonneborn_berger":0.0,"tpr":0,"tpr_mixed":0},{"average_rating_cut":1000.0,"buchholz":1.0,"buchholz_cut":1.0,"color_balance":1,"player":10,"progressive_score":0.0,"rank":36,"score":0.0,"sonneborn_berger":0.0,"tpr":0,"tpr_mixed":0},{"average_rating_cut":1000.0,"buchholz":1.0,"buchholz_cut":1.0,"color_balance":-1,"player":11,"progressive_score":0.0,"rank":37,"score":0.0,"sonneborn_berger":0.0,"tpr":0,"tpr_mixed":0},{"average_rating_cut":1000.0,"buchholz":1.0,"buchholz_cut":1.0,"color_balance":1,"player":14,"progressive_score":0.0,"rank":38,"score":0.0,"sonneborn_berger":0.0,"tpr":0,"tpr_mixed":0},{"average_rating_cut":1000.0,"buchholz":1.0,"buchholz_cut":1.0,"color_balance":1,"player":16,"progressive_score":0.0,"rank":39,"score":0.0,"sonneborn_berger":0.0,"tpr":0,"tpr_mixed":0},{"average_rating_cut":1000.0,"buchholz":1.0,"buchholz_cut":1.0,"color_balance":-1,"player":19,"progressive_score":0.0,"rank":40,"score":0.0,"sonneborn_berger":0.0,"tpr":0,"tpr_mixed":0},{"average_rating_cut":1000.0,"buchholz":1.0,"buchholz_cut":1.0,"color_balance":-1,"player":23,"progressive_score":0.0,"rank":41,"score":0.0,"sonneborn_berger":0.0,"tpr":0,"tpr_mixed":0},{"average_rating_cut":1000.0,"buchholz":1.0,"buchholz_cut":1.0,"color_balance":1,"player":24,"progressive_score":0.0,"rank":42,"score":0.0,"sonneborn_berger":0.0,"tpr":0,"tpr_mixed":0},{"average_rating_cut":1000.0,"buchholz":1.0,"buchholz_cut":1.0,"color_balance":-1,"player":25,"progressive_score":0.0,"rank":43,"score":0.0,"sonneborn_berger":0.0,"tpr":0,"tpr_mixed":0},{"average_rating_cut":1000.0,"buchholz":1.0,"buchholz_cut":1.0,"color_balance":1,"player":26,"progressive_score":0.0,"rank":44,"score":0.0,"sonneborn_berger":0.0,"tpr":0,"tpr_mixed":0},{"average_rating_cut":1000.0,"buchholz":1.0,"buchholz_cut":1.0,"color_balance":-1,"player":27,"progressive_score":0.0,"rank":45,"score":0.0,"sonneborn_berger":0.0,"tpr":0,"tpr_mixed":0},{"average_rating_cut":1000.0,"buchholz":1.0,"buchholz_cut":1.0,"color_balance":1,"player":28,"progressive_score":0.0,"rank":46,"score":0.0,"sonneborn_berger":0.0,"tpr":0,"tpr_mixed":0},{"average_rating_cut":1000.0,"buchholz":1.0,"buchholz_cut":1.0,"color_balance":1,"player":30,"progressive_score":0.0,"rank":47,"score":0.0,"sonneborn_berger":0.0,"tpr":0,"tpr_mixed":0},{"average_rating_cut":1000.0,"buchholz":1.0,"buchholz_cut":1.0,"color_balance":-1,"player":31,"progressive_score":0.0,"rank":48,"score":0.0,"sonneborn_berger":0.0,"tpr":0,"tpr_mixed":0},{"average_rating_cut":1000.0,"buchholz":1.0,"buchholz_cut":1.0,"color_balance":1,"player":32,"progressive_score":0.0,"rank":49,"score":0.0,"sonneborn_berger":0.0,"tpr":0,"tpr_mixed":0},{"average_rating_cut":1000.0,"buchholz":1.0,"buchholz_cut":1.0,"color_balance":1,"player":34,"progressive_score":0.0,"rank":50,"score":0.0,"sonneborn_berger":0.0,"tpr":0,"tpr_mixed":0},{"average_rating_cut":1000.0,"buchholz":1.0,"buchholz_cut":1.0,"color_balance":-1,"player":41,"progressive_score":0.0,"rank":51,"score":0.0,"sonneborn_berger":0.0,"tpr":0,"tpr_mixed":0},{"average_rating_cut":1000.0,"buchholz":1.0,"buchholz_cut":1.0,"color_balance":1,"player":42,"progressive_score":0.0,"rank":52,"score":0.0,"sonneborn_berger":0.0,"tpr":0,"tpr_mixed":0},{"average_rating_cut":1000.0,"buchholz":1.0,"buchholz_cut":1.0,"color_balance":1,"player":44,"progressive_score":0.0,"rank":53,"score":0.0,"sonneborn_berger":0.0,"tpr":0,"tpr_mixed":0},{"average_rating_cut":1000.0,"buchholz":1.0,"buchholz_cut":1.0,"color_balance":1,"player":46,"progressive_score":0.0,"rank":54,"score":0.0,"sonneborn_berger":0.0,"tpr":0,"tpr_mixed":0},{"average_rating_cut":1000.0,"buchholz":1.0,"buchholz_cut":1.0,"color_balance":-1,"player":47,"progressive_score":0.0,"rank":55,"score":0.0,"sonneborn_berger":0.0,"tpr":0,"tpr_mixed":0},{"average_rating_cut":1000.0,"buchholz":1.0,"buchholz_cut":1.0,"color_balance":-1,"player":49,"progressive_score":0.0,"rank":56,"score":0.0,"sonneborn_berger":0.0,"tpr":0,"tpr_mixed":0},{"average_rating_cut":1000.0,"buchholz":1.0,"buchholz_cut":1.0,"color_balance":1,"player":50,"progressive_score":0.0,"rank":57,"score":0.0,"sonneborn_berger":0.0,"tpr":0,"tpr_mixed":0},{"average_rating_cut":1000.0,"buchholz":1.0,"buchholz_cut":1.0,"color_balance":-1,"player":51,"progressive_score":0.0,"rank":58,"score":0.0,"sonneborn_berger":0.0,"tpr":0,"tpr_mixed":0},{"average_rating_cut":1000.0,"buchholz":1.0,"buchholz_cut":1.0,"color_balance":1,"player":58,"progressive_score":0.0,"rank":59,"score":0.0,"sonneborn_berger":0.0,"tpr":0,"tpr_mixed":0}]},{"byes":[{"pairing_allocated":true,"player":58,"score":1.0}],"date":"2025-09-13","number":2,"pairings":[{"black":36,"black_points":1.0,"table":1,"white":1,"white_points":0.0},{"black":2,"black_points":1.0,"table":2,"white":37,"white_points":0.0},{"black":38,"black_points":1.0,"table":3,"white":3,"white_points":0.0},{"black":39,"black_points":1.0,"table":4,"white":5,"white_points":0.0},{"black":12,"black_points":0.5,"table":5,"white":43,"white_points":0.5},{"black":40,"black_points":0.0,"table":6,"white":13,"white_points":1.0},{"black":45,"black_points":1.0,"table":7,"white":15,"white_points":0.0},{"black":48,"black_points":0.0,"table":8,"white":17,"white_points":1.0},{"black":18,"black_points":1.0,"table":9,"white":53,"white_points":0.0},{"black":20,"black_points":0.0,"table":10,"white":55,"white_points":1.0},{"black":52,"black_points":0.0,"table":11,"white":21,"white_points":1.0},{"black":22,"black_points":1.0,"table":12,"white":57,"white_points":0.0},{"black":54,"black_points":0.0,"table":13,"white":29,"white_points":1.0},{"black":56,"black_points":1.0,"table":14,"white":33,"white_points":0.0},{"black":59,"black_points":1.0,"table":15,"white":35,"white_points":0.0},{"black":4,"black_points":0.0,"table":16,"white":27,"white_points":1.0},{"black":6,"black_points":1.0,"table":17,"white":28,"white_points":0.0},{"black":30,"black_points":1.0,"table":18,"white":7,"white_points":0.0},{"black":8,"black_points":0.0,"table":19,"white":31,"white_points":1.0},{"black":32,"black_points":0.0,"table":20,"white":9,"white_points":1.0},{"black":10,"black_points":0.0,"table":21,"white":34,"white_points":1.0},{"black":42,"black_points":0.0,"table":22,"white":11,"white_points":1.0},{"black":14,"black_points":1.0,"table":23,"white":41,"white_points":0.0},{"black":16,"black_points":0.0,"table":24,"white":47,"white_points":1.0},{"black":44,"black_points":0.0,"table":25,"white":19,"white_points":1.0},{"black":46,"black_points":1.0,"table":26,"white":23,"white_points":0.0},{"black":24,"black_points":0.0,"table":27,"white":49,"white_points":1.0},{"black":50,"black_points":1.0,"table":28,"white":25,"white_points":0.0},{"black":26,"black_points":1.0,"table":29,"white":51,"white_points":0.0}],"ranking":[{"average_rating_cut":1000.0,"buchholz":2.0,"buchholz_cut":2.0,"color_balance":0,"mutual_result_top":0.0,"player":2,"progressive_score":3.0,"rank":1,"score":2.0,"sonneborn_berger":2.0,"tpr":0,"tpr_mixed":0},{"average_rating_cut":1000.0,"buchholz":2.0,"buchholz_cut":2.0,"color_balance":0,"mutual_result_top":0.0,"player":17,"progressive_score":3.0,"rank":2,"score":2.0,"sonneborn_berger":2.0,"tpr":0,"tpr_mixed":0},{"average_rating_cut":1000.0,"buchholz":2.0,"buchholz_cut":2.0,"color_balance":0,"mutual_result_top":0.0,"player":18,"progressive_score":3.0,"rank":3,"score":2.0,"sonneborn_berger":2.0,"tpr":0,"tpr_mixed":0},{"average_rating_cut":1000.0,"buchholz":2.0,"buchholz_cut":2.0,"color_balance":0,"mutual_result_top":0.0,"player":21,"progressive_score":3.0,"rank":4,"score":2.0,"sonneborn_berger":2.0,"tpr":0,"tpr_mixed":0},{"average_rating_cut":1000.0,"buchholz":2.0,"buchholz_cut":2.0,"color_balance":0,"mutual_result_top":0.0,"player":38,"progressive_score":3.0,"rank":5,"score":2.0,"sonneborn_berger":2.0,"tpr":0,"tpr_mixed":0},{"average_rating_cut":1000.0,"buchholz":2.0,"buchholz_cut":2.0,"color_balance":0,"mutual_result_top":0.0,"player":55,"progressive_score":3.0,"rank":6,"score":2.0,"sonneborn_berger":2.0,"tpr":0,"tpr_mixed":0},{"average_rating_cut":1000.0,"buchholz":2.0,"buchholz_cut":2.0,"color_balance":0,"mutual_result_top":0.0,"player":56,"progressive_score":3.0,"rank":7,"score":2.0,"sonneborn_berger":2.0,"tpr":0,"tpr_mixed":0},{"average_rating_cut":1000.0,"buchholz":1.5,"buchholz_cut":1.5,"color_balance":0,"mutual_result_top":0.0,"player":29,"progressive_score":3.0,"rank":8,"score":2.0,"sonneborn_berger":1.5,"tpr":0,"tpr_mixed":0},{"average_rating_cut":1000.0,"buchholz":1.5,"buchholz_cut":1.5,"color_balance":0,"mutual_result_top":0.0,"player":59,"progressive_score":3.0,"rank":9,"score":2.0,"sonneborn_berger":1.5,"tpr":0,"tpr_mixed":0},{"average_rating_cut":1000.0,"buchholz":1.0,"buchholz_cut":1.0,"color_balance":0,"mutual_result_top":0.0,"player":13,"progressive_score":3.0,"rank":10,"score":2.0,"sonneborn_berger":1.0,"tpr":0,"tpr_mixed":0},{"average_rating_cut":1000.0,"buchholz":1.0,"buchholz_cut":1.0,"color_balance":0,"mutual_result_top":0.0,"player":22,"progressive_score":3.0,"rank":11,"score":2.0,"sonneborn_berger":1.0,"tpr":0,"tpr_mixed":0},{"average_rating_cut":1000.0,"buchholz":1.0,"buchholz_cut":1.0,"color_balance":0,"mutual_result_top":0.0,"player":36,"progressive_score":3.0,"rank":12,"score":2.0,"sonneborn_berger":1.0,"tpr":0,"tpr_mixed":0},{"average_rating_cut":1000.0,"buchholz":1.0,"buchholz_cut":1.0,"color_balance":-2,"mutual_result_top":0.0,"player":39,"progressive_score":3.0,"rank":13,"score":2.0,"sonneborn_berger":1.0,"tpr":0,"tpr_mixed":0},{"average_rating_cut":1000.0,"buchholz":1.0,"buchholz_cut":1.0,"color_balance":-2,"mutual_result_top":0.0,"player":45,"progressive_score":3.0,"rank":14,"score":2.0,"sonneborn_berger":1.0,"tpr":0,"tpr_mixed":0},{"average_rating_cut":1000.0,"buchholz":2.5,"buchholz_cut":2.5,"color_balance":0,"player":43,"progressive_score":2.5,"rank":15,"score":1.5,"sonneborn_berger":1.75,"tpr":0,"tpr_mixed":0},{"average_rating_cut":1000.0,"buchholz":1.5,"buchholz_cut":1.5,"color_balance":0,"player":12,"progressive_score":2.5,"rank":16,"score":1.5,"sonneborn_berger":0.75,"tpr":0,"tpr_mixed":0},{"average_rating_cut":1000.0,"buchholz":3.0,"buchholz_cut":3.0,"color_balance":0,"player":1,"progressive_score":2.0,"rank":17,"score":1.0,"sonneborn_berger":1.0,"tpr":0,"tpr_mixed":0},{"average_rating_cut":1000.0,"buchholz":3.0,"buchholz_cut":3.0,"color_balance":0,"player":5,"progressive_score":2.0,"rank":18,"score":1.0,"sonneborn_berger":1.0,"tpr":0,"tpr_mixed":0},{"average_rating_cut":1000.0,"buchholz":3.0,"buchholz_cut":3.0,"color_balance":0,"player":20,"progressive_score":2.0,"rank":19,"score":1.0,"sonneborn_berger":1.0,"tpr":0,"tpr_mixed":0},{"average_rating_cut":1000.0,"buchholz":3.0,"buchholz_cut":3.0,"color_balance":0,"player":40,"progressive_score":2.0,"rank":20,"score":1.0,"sonneborn_berger":1.0,"tpr":0,"tpr_mixed":0},{"average_rating_cut":1000.0,"buchholz":3.0,"buchholz_cut":3.0,"color_balance":0,"player":48,"progressive_score":2.0,"rank":21,"score":1.0,"sonneborn_berger":1.0,"tpr":0,"tpr_mixed":0},{"average_rating_cut":1000.0,"buchholz":2.5,"buchholz_cut":2.5,"color_balance":0,"player":35,"progressive_score":2.0,"rank":22,"score":1.0,"sonneborn_berger":1.0,"tpr":0,"tpr_mixed":0},{"average_rating_cut":1000.0,"buchholz":2.0,"buchholz_cut":2.0,"color_balance":0,"player":3,"progressive_score":2.0,"rank":23,"score":1.0,"sonneborn_berger":0.0,"tpr":0,"tpr_mixed":0},{"average_rating_cut":1000.0,"buchholz":2.0,"buchholz_cut":2.0,"color_balance":0,"player":9,"progressive_score":1.0,"rank":24,"score":1.0,"sonneborn_berger":0.0,"tpr":0,"tpr_mixed":0},{"average_rating_cut":1000.0,"buchholz":2.0,"buchholz_cut":2.0,"color_balance":0,"player":15,"progressive_score":2.0,"rank":25,"score":1.0,"sonneborn_berger":0.0,"tpr":0,"tpr_mixed":0},{"average_rating_cut":1000.0,"buchholz":2.0,"buchholz_cut":2.0,"color_balance":0,"player":26,"progressive_score":1.0,"rank":26,"score":1.0,"sonneborn_berger":0.0,"tpr":0,"tpr_mixed":0},{"average_rating_cut":1000.0,"buchholz":2.0,"buchholz_cut":2.0,"color_balance":0,"player":27,"progressive_score":1.0,"rank":27,"score":1.0,"sonneborn_berger":0.0,"tpr":0,"tpr_mixed":0},{"average_rating_cut":1000.0,"buchholz":2.0,"buchholz_cut":2.0,"color_balance":0,"player":31,"progressive_score":1.0,"rank":28,"score":1.0,"sonneborn_berger":0.0,"tpr":0,"tpr_mixed":0},{"average_rating_cut":1000.0,"buchholz":2.0,"buchholz_cut":2.0,"color_balance":0,"player":33,"progressive_score":2.0,"rank":29,"score":1.0,"sonneborn_berger":0.0,"tpr":0,"tpr_mixed":0},{"average_rating_cut":1000.0,"buchholz":2.0,"buchholz_cut":2.0,"color_balance":0,"player":37,"progressive_score":2.0,"rank":30,"score":1.0,"sonneborn_berger":0.0,"tpr":0,"tpr_mixed":0},{"average_rating_cut":1000.0,"buchholz":2.0,"buchholz_cut":2.0,"color_balance":0,"player":46,"progressive_score":1.0,"rank":31,"score":1.0,"sonneborn_berger":0.0,"tpr":0,"tpr_mixed":0},{"average_rating_cut":1000.0,"buchholz":2.0,"buchholz_cut":2.0,"color_balance":0,"player":47,"progressive_score":1.0,"rank":32,"score":1.0,"sonneborn_berger":0.0,"tpr":0,"tpr_mixed":0},{"average_rating_cut":1000.0,"buchholz":2.0,"buchholz_cut":2.0,"color_balance":0,"player":50,"progressive_score":1.0,"rank":33,"score":1.0,"sonneborn_berger":0.0,"tpr":0,"tpr_mixed":0},{"average_rating_cut":1000.0,"buchholz":2.0,"buchholz_cut":2.0,"color_balance":0,"player":52,"progressive_score":2.0,"rank":34,"score":1.0,"sonneborn_berger":0.0,"tpr":0,"tpr_mixed":0},{"average_rating_cut":1000.0,"buchholz":2.0,"buchholz_cut":2.0,"color_balance":0,"player":53,"progressive_score":2.0,"rank":35,"score":1.0,"sonneborn_berger":0.0,"tpr":0,"tpr_mixed":0},{"average_rating_cut":1000.0,"buchholz":2.0,"buchholz_cut":2.0,"color_balance":0,"player":54,"progressive_score":2.0,"rank":36,"score":1.0,"sonneborn_berger":0.0,"tpr":0,"tpr_mixed":0},{"average_rating_cut":1000.0,"buchholz":2.0,"buchholz_cut":2.0,"color_balance":0,"player":57,"progressive_score":2.0,"rank":37,"score":1.0,"sonneborn_berger":0.0,"tpr":0,"tpr_mixed":0},{"average_rating_cut":1000.0,"buchholz":2.0,"buchholz_cut":2.0,"color_balance":2,"player":58,"progressive_score":1.0,"rank":38,"score":1.0,"sonneborn_berger":0.0,"tpr":0,"tpr_mixed":0},{"average_rating_cut":1000.0,"buchholz":1.5,"buchholz_cut":1.5,"color_balance":0,"player":14,"progressive_score":1.0,"rank":39,"score":1.0,"sonneborn_berger":0.0,"tpr":0,"tpr_mixed":0},{"average_rating_cut":1000.0,"buchholz":1.0,"buchholz_cut":1.0,"color_balance":0,"player":6,"progressive_score":1.0,"rank":40,"score":1.0,"sonneborn_berger":0.0,"tpr":0,"tpr_mixed":0},{"average_rating_cut":1000.0,"buchholz":1.0,"buchholz_cut":1.0,"color_balance":0,"player":11,"progressive_score":1.0,"rank":41,"score":1.0,"sonneborn_berger":0.0,"tpr":0,"tpr_mixed":0},{"average_rating_cut":1000.0,"buchholz":1.0,"buchholz_cut":1.0,"color_balance":0,"player":19,"progressive_score":1.0,"rank":42,"score":1.0,"sonneborn_berger":0.0,"tpr":0,"tpr_mixed":0},{"average_rating_cut":1000.0,"buchholz":1.0,"buchholz_cut":1.0,"color_balance":0,"player":30,"progressive_score":1.0,"rank":43,"score":1.0,"sonneborn_berger":0.0,"tpr":0,"tpr_mixed":0},{"average_rating_cut":1000.0,"buchholz":1.0,"buchholz_cut":1.0,"color_balance":2,"player":34,"progressive_score":1.0,"rank":44,"score":1.0,"sonneborn_berger":0.0,"tpr":0,"tpr_mixed":0},{"average_rating_cut":1000.0,"buchholz":1.0,"buchholz_cut":1.0,"color_balance":0,"player":49,"progressive_score":1.0,"rank":45,"score":1.0,"sonneborn_berger":0.0,"tpr":0,"tpr_mixed":0},{"average_rating_cut":1000.0,"buchholz":3.0,"buchholz_cut":3.0,"color_balance":0,"player":7,"progressive_score":0.0,"rank":46,"score":0.0,"sonneborn_berger":0.0,"tpr":0,"tpr_mixed":0},{"average_rating_cut":1000.0,"buchholz":3.0,"buchholz_cut":3.0,"color_balance":0,"player":10,"progressive_score":0.0,"rank":47,"score":0.0,"sonneborn_berger":0.0,"tpr":0,"tpr_mixed":0},{"average_rating_cut":1000.0,"buchholz":3.0,"buchholz_cut":3.0,"color_balance":0,"player":16,"progressive_score":0.0,"rank":48,"score":0.0,"sonneborn_berger":0.0,"tpr":0,"tpr_mixed":0},{"average_rating_cut":1000.0,"buchholz":3.0,"buchholz_cut":3.0,"color_balance":0,"player":42,"progressive_score":0.0,"rank":49,"score":0.0,"sonneborn_berger":0.0,"tpr":0,"tpr_mixed":0},{"average_rating_cut":1000.0,"buchholz":3.0,"buchholz_cut":3.0,"color_balance":0,"player":51,"progressive_score":0.0,"rank":50,"score":0.0,"sonneborn_berger":0.0,"tpr":0,"tpr_mixed":0},{"average_rating_cut":1000.0,"buchholz":2.5,"buchholz_cut":2.5,"color_balance":0,"player":41,"progressive_score":0.0,"rank":51,"score":0.0,"sonneborn_berger":0.0,"tpr":0,"tpr_mixed":0},{"average_rating_cut":1000.0,"buchholz":2.0,"buchholz_cut":2.0,"color_balance":0,"player":4,"progressive_score":0.0,"rank":52,"score":0.0,"sonneborn_berger":0.0,"tpr":0,"tpr_mixed":0},{"average_rating_cut":1000.0,"buchholz":2.0,"buchholz_cut":2.0,"color_balance":0,"player":8,"progressive_score":0.0,"rank":53,"score":0.0,"sonneborn_berger":0.0,"tpr":0,"tpr_mixed":0},{"average_rating_cut":1000.0,"buchholz":2.0,"buchholz_cut":2.0,"color_balance":0,"player":23,"progressive_score":0.0,"rank":54,"score":0.0,"sonneborn_berger":0.0,"tpr":0,"tpr_mixed":0},{"average_rating_cut":1000.0,"buchholz":2.0,"buchholz_cut":2.0,"color_balance":0,"player":24,"progressive_score":0.0,"rank":55,"score":0.0,"sonneborn_berger":0.0,"tpr":0,"tpr_mixed":0},{"average_rating_cut":1000.0,"buchholz":2.0,"buchholz_cut":2.0,"color_balance":0,"player":25,"progressive_score":0.0,"rank":56,"score":0.0,"sonneborn_berger":0.0,"tpr":0,"tpr_mixed":0},{"average_rating_cut":1000.0,"buchholz":2.0,"buchholz_cut":2.0,"color_balance":2,"player":28,"progressive_score":0.0,"rank":57,"score":0.0,"sonneborn_berger":0.0,"tpr":0,"tpr_mixed":0},{"average_rating_cut":1000.0,"buchholz":2.0,"buchholz_cut":2.0,"color_balance":0,"player":32,"progressive_score":0.0,"rank":58,"score":0.0,"sonneborn_berger":0.0,"tpr":0,"tpr_mixed":0},{"average_rating_cut":1000.0,"buchholz":2.0,"buchholz_cut":2.0,"color_balance":0,"player":44,"progressive_score":0.0,"rank":59,"score":0.0,"sonneborn_berger":0.0,"tpr":0,"tpr_mixed":0}]},{"byes":[{"player":6,"score":0.0},{"player":10,"score":0.0},{"player":30,"score":0.0},{"pairing_allocated":true,"player":44,"score":1.0},{"player":57,"score":0.0}],"date":"2025-09-13","number":3,"pairings":[{"black":36,"black_points":1.0,"table":1,"white":2,"white_points":0.0},{"black":13,"black_points":1.0,"table":2,"white":38,"white_points":0.0},{"black":17,"black_points":1.0,"table":3,"white":39,"white_points":0.0},{"black":18,"black_points":0.0,"table":4,"white":45,"white_points":1.0},{"black":21,"black_points":1.0,"table":5,"white":56,"white_points":0.0},{"black":55,"black_points":0.0,"table":6,"white":22,"white_points":1.0},{"black":29,"black_points":0.0,"table":7,"white":59,"white_points":1.0},{"black":1,"black_points":0.0,"table":8,"white":12,"white_points":1.0},{"black":43,"black_points":1.0,"table":9,"white":3,"white_points":0.0},{"black":5,"black_points":0.0,"table":10,"white":35,"white_points":1.0},{"black":9,"black_points":1.0,"table":11,"white":37,"white_points":0.0},{"black":11,"black_points":0.0,"table":12,"white":46,"white_points":1.0},{"black":47,"black_points":0.0,"table":13,"white":14,"white_points":1.0},{"black":15,"black_points":0.0,"table":14,"white":40,"white_points":1.0},{"black":19,"black_points":1.0,"table":15,"white":49,"white_points":0.0},{"black":53,"black_points":0.0,"table":16,"white":20,"white_points":1.0},{"black":58,"black_points":0.0,"table":17,"white":26,"white_points":1.0},{"black":27,"black_points":0.0,"table":18,"white":48,"white_points":1.0},{"black":31,"black_points":0.5,"table":19,"white":50,"white_points":0.5},{"black":33,"black_points":0.0,"table":20,"white":52,"white_points":1.0},{"black":34,"black_points":1.0,"table":21,"white":54,"white_points":0.0},{"black":25,"black_points":1.0,"table":22,"white":4,"white_points":0.0},{"black":7,"black_points":1.0,"table":23,"white":32,"white_points":0.0},{"black":28,"black_points":1.0,"table":24,"white":8,"white_points":0.0},{"black":41,"black_points":0.0,"table":25,"white":16,"white_points":1.0},{"black":23,"black_points":0.0,"table":26,"white":42,"white_points":1.0},{"black":51,"black_points":1.0,"table":27,"white":24,"white_points":0.0}],"ranking":[{"average_rating_cut":1000.0,"buchholz":6.0,"buchholz_cut":4.0,"color_balance":-1,"mutual_result_top":0.0,"player":17,"progressive_score":6.0,"rank":1,"score":3.0,"sonneborn_berger":6.0,"tpr":0,"tpr_mixed":0},{"average_rating_cut":1000.0,"buchholz":5.5,"buchholz_cut":4.0,"color_balance":-1,"mutual_result_top":0.0,"player":21,"progressive_score":6.0,"rank":2,"score":3.0,"sonneborn_berger":5.5,"tpr":0,"tpr_mixed":0},{"average_rating_cut":1000.0,"buchholz":5.0,"buchholz_cut":4.0,"color_balance":-1,"mutual_result_top":0.0,"player":13,"progressive_score":6.0,"rank":3,"score":3.0,"sonneborn_berger":5.0,"tpr":0,"tpr_mixed":0},{"average_rating_cut":1000.0,"buchholz":5.0,"buchholz_cut":4.0,"color_balance":1,"mutual_result_top":0.0,"player":59,"progressive_score":6.0,"rank":4,"score":3.0,"sonneborn_berger":5.0,"tpr":0,"tpr_mixed":0},{"average_rating_cut":1000.0,"buchholz":4.5,"buchholz_cut":3.5,"color_balance":1,"mutual_result_top":0.0,"player":22,"progressive_score":6.0,"rank":5,"score":3.0,"sonneborn_berger":4.5,"tpr":0,"tpr_mixed":0},{"average_rating_cut":1000.0,"buchholz":4.0,"buchholz_cut":3.0,"color_balance":-1,"mutual_result_top":0.0,"player":36,"progressive_score":6.0,"rank":6,"score":3.0,"sonneborn_berger":4.0,"tpr":0,"tpr_mixed":0},{"average_rating_cut":1000.0,"buchholz":4.0,"buchholz_cut":3.0,"color_balance":-1,"mutual_result_top":0.0,"player":45,"progressive_score":6.0,"rank":7,"score":3.0,"sonneborn_berger":4.0,"tpr":0,"tpr_mixed":0},{"average_rating_cut":1000.0,"buchholz":5.5,"buchholz_cut":4.5,"color_balance":-1,"player":43,"progressive_score":5.0,"rank":8,"score":2.5,"sonneborn_berger":4.25,"tpr":0,"tpr_mixed":0},{"average_rating_cut":1000.0,"buchholz":3.5,"buchholz_cut":3.5,"color_balance":1,"player":12,"progressive_score":5.0,"rank":9,"score":2.5,"sonneborn_berger":2.25,"tpr":0,"tpr_mixed":0},{"average_rating_cut":1000.0,"buchholz":7.0,"buchholz_cut":5.0,"color_balance":-1,"player":55,"progressive_score":5.0,"rank":10,"score":2.0,"sonneborn_berger":4.0,"tpr":0,"tpr_mixed":0},{"average_rating_cut":1000.0,"buchholz":6.0,"buchholz_cut":5.0,"color_balance":1,"player":38,"progressive_score":5.0,"rank":11,"score":2.0,"sonneborn_berger":3.0,"tpr":0,"tpr_mixed":0},{"average_rating_cut":1000.0,"buchholz":6.0,"buchholz_cut":5.0,"color_balance":1,"player":48,"progressive_score":4.0,"rank":12,"score":2.0,"sonneborn_berger":3.0,"tpr":0,"tpr_mixed":0},{"average_rating_cut":1000.0,"buchholz":5.5,"buchholz_cut":4.5,"color_balance":1,"player":2,"progressive_score":5.0,"rank":13,"score":2.0,"sonneborn_berger":2.5,"tpr":0,"tpr_mixed":0},{"average_rating_cut":1000.0,"buchholz":5.0,"buchholz_cut":4.0,"color_balance":1,"player":35,"progressive_score":4.0,"rank":14,"score":2.0,"sonneborn_berger":2.5,"tpr":0,"tpr_mixed":0},{"average_rating_cut":1000.0,"buchholz":5.0,"buchholz_cut":4.0,"color_balance":-1,"player":18,"progressive_score":5.0,"rank":15,"score":2.0,"sonneborn_berger":2.0,"tpr":0,"tpr_mixed":0},{"average_rating_cut":1000.0,"buchholz":5.0,"buchholz_cut":4.0,"color_balance":1,"player":40,"progressive_score":4.0,"rank":16,"score":2.0,"sonneborn_berger":2.0,"tpr":0,"tpr_mixed":0},{"average_rating_cut":1000.0,"buchholz":5.0,"buchholz_cut":4.0,"color_balance":1,"player":56,"progressive_score":5.0,"rank":17,"score":2.0,"sonneborn_berger":2.0,"tpr":0,"tpr_mixed":0},{"average_rating_cut":1000.0,"buchholz":4.5,"buchholz_cut":4.0,"color_balance":-1,"player":39,"progressive_score":5.0,"rank":18,"score":2.0,"sonneborn_berger":1.5,"tpr":0,"tpr_mixed":0},{"average_rating_cut":1000.0,"buchholz":4.0,"buchholz_cut":3.0,"color_balance":1,"player":20,"progressive_score":4.0,"rank":19,"score":2.0,"sonneborn_berger":2.0,"tpr":0,"tpr_mixed":0},{"average_rating_cut":1000.0,"buchholz":4.0,"buchholz_cut":3.5,"color_balance":-1,"player":29,"progressive_score":5.0,"rank":20,"score":2.0,"sonneborn_berger":1.5,"tpr":0,"tpr_mixed":0},{"average_rating_cut":1000.0,"buchholz":4.0,"buchholz_cut":4.0,"color_balance":1,"player":46,"progressive_score":3.0,"rank":21,"score":2.0,"sonneborn_berger":1.0,"tpr":0,"tpr_mixed":0},{"average_rating_cut":1000.0,"buchholz":4.0,"buchholz_cut":4.0,"color_balance":1,"player":52,"progressive_score":4.0,"rank":22,"score":2.0,"sonneborn_berger":1.0,"tpr":0,"tpr_mixed":0},{"average_rating_cut":1000.0,"buchholz":3.5,"buchholz_cut":3.0,"color_balance":-1,"player":19,"progressive_score":3.0,"rank":23,"score":2.0,"sonneborn_berger":1.5,"tpr":0,"tpr_mixed":0},{"average_rating_cut":1000.0,"buchholz":3.5,"buchholz_cut":3.0,"color_balance":1,"player":26,"progressive_score":3.0,"rank":24,"score":2.0,"sonneborn_berger":1.5,"tpr":0,"tpr_mixed":0},{"average_rating_cut":1000.0,"buchholz":3.5,"buchholz_cut":3.5,"color_balance":1,"player":14,"progressive_score":3.0,"rank":25,"score":2.0,"sonneborn_berger":1.0,"tpr":0,"tpr_mixed":0},{"average_rating_cut":1000.0,"buchholz":3.0,"buchholz_cut":3.0,"color_balance":-1,"player":9,"progressive_score":3.0,"rank":26,"score":2.0,"sonneborn_berger":1.0,"tpr":0,"tpr_mixed":0},{"average_rating_cut":1000.0,"buchholz":2.5,"buchholz_cut":2.0,"color_balance":1,"player":34,"progressive_score":3.0,"rank":27,"score":2.0,"sonneborn_berger":1.5,"tpr":0,"tpr_mixed":0},{"average_rating_cut":1000.0,"buchholz":5.5,"buchholz_cut":4.5,"color_balance":1,"player":50,"progressive_score":2.5,"rank":28,"score":1.5,"sonneborn_berger":1.75,"tpr":0,"tpr_mixed":0},{"average_rating_cut":1000.0,"buchholz":3.5,"buchholz_cut":3.5,"color_balance":-1,"player":31,"progressive_score":2.5,"rank":29,"score":1.5,"sonneborn_berger":0.75,"tpr":0,"tpr_mixed":0},{"average_rating_cut":1000.0,"buchholz":7.0,"buchholz_cut":5.5,"color_balance":-1,"player":1,"progressive_score":3.0,"rank":30,"score":1.0,"sonneborn_berger":1.5,"tpr":0,"tpr_mixed":0},{"average_rating_cut":1000.0,"buchholz":6.0,"buchholz_cut":4.0,"color_balance":-1,"player":5,"progressive_score":3.0,"rank":31,"score":1.0,"sonneborn_berger":2.0,"tpr":0,"tpr_mixed":0},{"average_rating_cut":1000.0,"buchholz":6.0,"buchholz_cut":5.0,"color_balance":1,"player":57,"progressive_score":3.0,"rank":32,"score":1.0,"sonneborn_berger":1.0,"tpr":0,"tpr_mixed":0},{"average_rating_cut":1000.0,"buchholz":5.5,"buchholz_cut":5.0,"color_balance":-1,"player":15,"progressive_score":3.0,"rank":33,"score":1.0,"sonneborn_berger":0.5,"tpr":0,"tpr_mixed":0},{"average_rating_cut":1000.0,"buchholz":5.0,"buchholz_cut":4.0,"color_balance":1,"player":6,"progressive_score":2.0,"rank":34,"score":1.0,"sonneborn_berger":1.0,"tpr":0,"tpr_mixed":0},{"average_rating_cut":1000.0,"buchholz":5.0,"buchholz_cut":4.0,"color_balance":-1,"player":11,"progressive_score":2.0,"rank":35,"score":1.0,"sonneborn_berger":1.0,"tpr":0,"tpr_mixed":0},{"average_rating_cut":1000.0,"buchholz":5.0,"buchholz_cut":4.0,"color_balance":-1,"player":47,"progressive_score":2.0,"rank":36,"score":1.0,"sonneborn_berger":1.0,"tpr":0,"tpr_mixed":0},{"average_rating_cut":1000.0,"buchholz":5.0,"buchholz_cut":4.0,"color_balance":1,"player":54,"progressive_score":3.0,"rank":37,"score":1.0,"sonneborn_berger":1.0,"tpr":0,"tpr_mixed":0},{"average_rating_cut":1000.0,"buchholz":5.0,"buchholz_cut":5.0,"color_balance":-1,"player":51,"progressive_score":1.0,"rank":38,"score":1.0,"sonneborn_berger":0.0,"tpr":0,"tpr_mixed":0},{"average_rating_cut":1000.0,"buchholz":4.5,"buchholz_cut":4.0,"color_balance":1,"player":58,"progressive_score":2.0,"rank":39,"score":1.0,"sonneborn_berger":0.5,"tpr":0,"tpr_mixed":0},{"average_rating_cut":1000.0,"buchholz":4.5,"buchholz_cut":4.5,"color_balance":1,"player":3,"progressive_score":3.0,"rank":40,"score":1.0,"sonneborn_berger":0.0,"tpr":0,"tpr_mixed":0},{"average_rating_cut":1000.0,"buchholz":4.5,"buchholz_cut":4.5,"color_balance":-1,"player":7,"progressive_score":1.0,"rank":41,"score":1.0,"sonneborn_berger":0.0,"tpr":0,"tpr_mixed":0},{"average_rating_cut":1000.0,"buchholz":4.0,"buchholz_cut":3.0,"color_balance":1,"player":30,"progressive_score":2.0,"rank":42,"score":1.0,"sonneborn_berger":1.0,"tpr":0,"tpr_mixed":0},{"average_rating_cut":1000.0,"buchholz":4.0,"buchholz_cut":4.0,"color_balance":1,"player":16,"progressive_score":1.0,"rank":43,"score":1.0,"sonneborn_berger":0.0,"tpr":0,"tpr_mixed":0},{"average_rating_cut":1000.0,"buchholz":4.0,"buchholz_cut":4.0,"color_balance":-1,"player":27,"progressive_score":2.0,"rank":44,"score":1.0,"sonneborn_berger":0.0,"tpr":0,"tpr_mixed":0},{"average_rating_cut":1000.0,"buchholz":4.0,"buchholz_cut":4.0,"color_balance":-1,"player":33,"progressive_score":3.0,"rank":45,"score":1.0,"sonneborn_berger":0.0,"tpr":0,"tpr_mixed":0},{"average_rating_cut":1000.0,"buchholz":4.0,"buchholz_cut":4.0,"color_balance":1,"player":37,"progressive_score":3.0,"rank":46,"score":1.0,"sonneborn_berger":0.0,"tpr":0,"tpr_mixed":0},{"average_rating_cut":1000.0,"buchholz":4.0,"buchholz_cut":4.0,"color_balance":1,"player":42,"progressive_score":1.0,"rank":47,"score":1.0,"sonneborn_berger":0.0,"tpr":0,"tpr_mixed":0},{"average_rating_cut":1000.0,"buchholz":4.0,"buchholz_cut":4.0,"color_balance":1,"player":49,"progressive_score":2.0,"rank":48,"score":1.0,"sonneborn_berger":0.0,"tpr":0,"tpr_mixed":0},{"average_rating_cut":1000.0,"buchholz":4.0,"buchholz_cut":4.0,"color_balance":-1,"player":53,"progressive_score":3.0,"rank":49,"score":1.0,"sonneborn_berger":0.0,"tpr":0,"tpr_mixed":0},{"average_rating_cut":1000.0,"buchholz":3.0,"buchholz_cut":3.0,"color_balance":1,"player":28,"progressive_score":1.0,"rank":50,"score":1.0,"sonneborn_berger":0.0,"tpr":0,"tpr_mixed":0},{"average_rating_cut":1000.0,"buchholz":3.0,"buchholz_cut":3.0,"color_balance":1,"player":44,"progressive_score":1.0,"rank":51,"score":1.0,"sonneborn_berger":0.0,"tpr":0,"tpr_mixed":0},{"average_rating_cut":1000.0,"buchholz":2.5,"buchholz_cut":2.5,"color_balance":-1,"player":25,"progressive_score":1.0,"rank":52,"score":1.0,"sonneborn_berger":0.0,"tpr":0,"tpr_mixed":0},{"average_rating_cut":1000.0,"buchholz":5.5,"buchholz_cut":4.5,"color_balance":-1,"player":41,"progressive_score":0.0,"rank":53,"score":0.0,"sonneborn_berger":0.0,"tpr":0,"tpr_mixed":0},{"average_rating_cut":1000.0,"buchholz":5.0,"buchholz_cut":4.0,"color_balance":1,"player":10,"progressive_score":0.0,"rank":54,"score":0.0,"sonneborn_berger":0.0,"tpr":0,"tpr_mixed":0},{"average_rating_cut":1000.0,"buchholz":5.0,"buchholz_cut":4.0,"color_balance":-1,"player":23,"progressive_score":0.0,"rank":55,"score":0.0,"sonneborn_berger":0.0,"tpr":0,"tpr_mixed":0},{"average_rating_cut":1000.0,"buchholz":4.0,"buchholz_cut":3.0,"color_balance":1,"player":32,"progressive_score":0.0,"rank":56,"score":0.0,"sonneborn_berger":0.0,"tpr":0,"tpr_mixed":0},{"average_rating_cut":1000.0,"buchholz":3.5,"buchholz_cut":2.5,"color_balance":1,"player":8,"progressive_score":0.0,"rank":57,"score":0.0,"sonneborn_berger":0.0,"tpr":0,"tpr_mixed":0},{"average_rating_cut":1000.0,"buchholz":3.0,"buchholz_cut":2.0,"color_balance":1,"player":4,"progressive_score":0.0,"rank":58,"score":0.0,"sonneborn_berger":0.0,"tpr":0,"tpr_mixed":0},{"average_rating_cut":1000.0,"buchholz":3.0,"buchholz_cut":2.0,"color_balance":1,"player":24,"progressive_score":0.0,"rank":59,"score":0.0,"sonneborn_berger":0.0,"tpr":0,"tpr_mixed":0}]},{"byes":[{"player":3,"score":0.0},{"player":4,"score":0.0},{"player":5,"score":0.0},{"player":6,"score":0.0},{"player":8,"score":0.0},{"player":10,"score":0.0},{"player":30,"score":0.0},{"pairing_allocated":true,"player":41,"score":1.0},{"player":57,"score":0.0}],"date":"2025-09-13","number":4,"pairings":[{"black":22,"black_points":0.0,"table":1,"white":13,"white_points":1.0},{"black":17,"black_points":1.0,"table":2,"white":36,"white_points":0.0},{"black":59,"black_points":0.0,"table":3,"white":21,"white_points":1.0},{"black":12,"black_points":1.0,"table":4,"white":45,"white_points":0.0},{"black":2,"black_points":0.0,"table":5,"white":43,"white_points":1.0},{"black":35,"black_points":1.0,"table":6,"white":9,"white_points":0.0},{"black":14,"black_points":0.5,"table":7,"white":38,"white_points":0.5},{"black":40,"black_points":0.0,"table":8,"white":18,"white_points":1.0},{"black":46,"black_points":1.0,"table":9,"white":19,"white_points":0.0},{"black":20,"black_points":0.0,"table":10,"white":39,"white_points":1.0},{"black":26,"black_points":0.0,"table":11,"white":48,"white_points":1.0},{"black":52,"black_points":1.0,"table":12,"white":29,"white_points":0.0},{"black":34,"black_points":0.0,"table":13,"white":55,"white_points":1.0},{"black":56,"black_points":0.0,"table":14,"white":31,"white_points":1.0},{"black":50,"black_points":1.0,"table":15,"white":7,"white_points":0.0},{"black":37,"black_points":0.0,"table":16,"white":1,"white_points":1.0},{"black":44,"black_points":0.0,"table":17,"white":11,"white_points":1.0},{"black":42,"black_points":1.0,"table":18,"white":15,"white_points":0.0},{"black":16,"black_points":1.0,"table":19,"white":51,"white_points":0.0},{"black":49,"black_points":1.0,"table":20,"white":25,"white_points":0.0},{"black":54,"black_points":0.5,"table":21,"white":27,"white_points":0.5},{"black":28,"black_points":0.0,"table":22,"white":47,"white_points":1.0},{"black":58,"black_points":0.0,"table":23,"white":33,"white_points":1.0},{"black":32,"black_points":0.0,"table":24,"white":53,"white_points":1.0},{"black":24,"black_points":0.0,"table":25,"white":23,"white_points":1.0}],"ranking":[{"average_rating_cut":1000.0,"buchholz":12.0,"buchholz_cut":6.0,"color_balance":-2,"mutual_result_top":0.0,"player":17,"progressive_score":10.0,"rank":1,"score":4.0,"sonneborn_berger":12.0,"tpr":0,"tpr_mixed":0},{"average_rating_cut":1000.0,"buchholz":10.0,"buchholz_cut":5.0,"color_balance":0,"mutual_result_top":0.0,"player":21,"progressive_score":10.0,"rank":2,"score":4.0,"sonneborn_berger":10.0,"tpr":0,"tpr_mixed":0},{"average_rating_cut":1000.0,"buchholz":9.5,"buchholz_cut":4.5,"color_balance":0,"mutual_result_top":0.0,"player":13,"progressive_score":10.0,"rank":3,"score":4.0,"sonneborn_berger":9.5,"tpr":0,"tpr_mixed":0},{"average_rating_cut":1000.0,"buchholz":9.5,"buchholz_cut":4.5,"color_balance":0,"player":43,"progressive_score":8.5,"rank":4,"score":3.5,"sonneborn_berger":7.75,"tpr":0,"tpr_mixed":0},{"average_rating_cut":1000.0,"buchholz":9.0,"buchholz_cut":5.0,"color_balance":0,"player":12,"progressive_score":8.5,"rank":5,"score":3.5,"sonneborn_berger":7.25,"tpr":0,"tpr_mixed":0},{"average_rating_cut":1000.0,"buchholz":10.5,"buchholz_cut":5.0,"color_balance":0,"player":59,"progressive_score":9.0,"rank":6,"score":3.0,"sonneborn_berger":6.5,"tpr":0,"tpr_mixed":0},{"average_rating_cut":1000.0,"buchholz":10.0,"buchholz_cut":5.0,"color_balance":0,"player":22,"progressive_score":9.0,"rank":7,"score":3.0,"sonneborn_berger":6.0,"tpr":0,"tpr_mixed":0},{"average_rating_cut":1000.0,"buchholz":9.5,"buchholz_cut":5.0,"color_balance":0,"player":45,"progressive_score":9.0,"rank":8,"score":3.0,"sonneborn_berger":6.0,"tpr":0,"tpr_mixed":0},{"average_rating_cut":1000.0,"buchholz":9.5,"buchholz_cut":4.0,"color_balance":2,"player":48,"progressive_score":7.0,"rank":9,"score":3.0,"sonneborn_berger":5.5,"tpr":0,"tpr_mixed":0},{"average_rating_cut":1000.0,"buchholz":9.0,"buchholz_cut":4.0,"color_balance":0,"player":18,"progressive_score":8.0,"rank":10,"score":3.0,"sonneborn_berger":6.0,"tpr":0,"tpr_mixed":0},{"average_rating_cut":1000.0,"buchholz":9.0,"buchholz_cut":4.0,"color_balance":0,"player":55,"progressive_score":8.0,"rank":11,"score":3.0,"sonneborn_berger":6.0,"tpr":0,"tpr_mixed":0},{"average_rating_cut":1000.0,"buchholz":9.0,"buchholz_cut":4.0,"color_balance":0,"player":36,"progressive_score":9.0,"rank":12,"score":3.0,"sonneborn_berger":5.0,"tpr":0,"tpr_mixed":0},{"average_rating_cut":1000.0,"buchholz":9.0,"buchholz_cut":4.0,"color_balance":0,"player":46,"progressive_score":6.0,"rank":13,"score":3.0,"sonneborn_berger":5.0,"tpr":0,"tpr_mixed":0},{"average_rating_cut":1000.0,"buchholz":9.0,"buchholz_cut":4.0,"color_balance":0,"player":52,"progressive_score":7.0,"rank":14,"score":3.0,"sonneborn_berger":5.0,"tpr":0,"tpr_mixed":0},{"average_rating_cut":1000.0,"buchholz":8.5,"buchholz_cut":3.5,"color_balance":0,"player":39,"progressive_score":8.0,"rank":15,"score":3.0,"sonneborn_berger":4.5,"tpr":0,"tpr_mixed":0},{"average_rating_cut":1000.0,"buchholz":8.0,"buchholz_cut":4.0,"color_balance":0,"player":35,"progressive_score":7.0,"rank":16,"score":3.0,"sonneborn_berger":5.5,"tpr":0,"tpr_mixed":0},{"average_rating_cut":1000.0,"buchholz":10.0,"buchholz_cut":4.5,"color_balance":2,"player":38,"progressive_score":7.5,"rank":17,"score":2.5,"sonneborn_berger":4.75,"tpr":0,"tpr_mixed":0},{"average_rating_cut":1000.0,"buchholz":8.5,"buchholz_cut":4.5,"color_balance":0,"player":14,"progressive_score":5.5,"rank":18,"score":2.5,"sonneborn_berger":3.75,"tpr":0,"tpr_mixed":0},{"average_rating_cut":1000.0,"buchholz":8.5,"buchholz_cut":3.5,"color_balance":0,"player":50,"progressive_score":5.0,"rank":19,"score":2.5,"sonneborn_berger":3.25,"tpr":0,"tpr_mixed":0},{"average_rating_cut":1000.0,"buchholz":7.0,"buchholz_cut":4.0,"color_balance":0,"player":31,"progressive_score":5.0,"rank":20,"score":2.5,"sonneborn_berger":3.75,"tpr":0,"tpr_mixed":0},{"average_rating_cut":1000.0,"buchholz":10.0,"buchholz_cut":5.0,"color_balance":0,"player":20,"progressive_score":6.0,"rank":21,"score":2.0,"sonneborn_berger":4.0,"tpr":0,"tpr_mixed":0},{"average_rating_cut":1000.0,"buchholz":10.0,"buchholz_cut":5.5,"color_balance":0,"player":2,"progressive_score":7.0,"rank":22,"score":2.0,"sonneborn_berger":3.5,"tpr":0,"tpr_mixed":0},{"average_rating_cut":1000.0,"buchholz":10.0,"buchholz_cut":4.5,"color_balance":0,"player":56,"progressive_score":7.0,"rank":23,"score":2.0,"sonneborn_berger":3.5,"tpr":0,"tpr_mixed":0},{"average_rating_cut":1000.0,"buchholz":10.0,"buchholz_cut":5.0,"color_balance":0,"player":40,"progressive_score":6.0,"rank":24,"score":2.0,"sonneborn_berger":3.0,"tpr":0,"tpr_mixed":0},{"average_rating_cut":1000.0,"buchholz":9.5,"buchholz_cut":5.0,"color_balance":0,"player":1,"progressive_score":5.0,"rank":25,"score":2.0,"sonneborn_berger":3.0,"tpr":0,"tpr_mixed":0},{"average_rating_cut":1000.0,"buchholz":8.5,"buchholz_cut":4.5,"color_balance":0,"player":47,"progressive_score":4.0,"rank":26,"score":2.0,"sonneborn_berger":3.0,"tpr":0,"tpr_mixed":0},{"average_rating_cut":1000.0,"buchholz":8.5,"buchholz_cut":5.0,"color_balance":0,"player":19,"progressive_score":5.0,"rank":27,"score":2.0,"sonneborn_berger":2.5,"tpr":0,"tpr_mixed":0},{"average_rating_cut":1000.0,"buchholz":8.0,"buchholz_cut":3.0,"color_balance":0,"player":42,"progressive_score":3.0,"rank":28,"score":2.0,"sonneborn_berger":2.0,"tpr":0,"tpr_mixed":0},{"average_rating_cut":1000.0,"buchholz":7.5,"buchholz_cut":4.0,"color_balance":0,"player":11,"progressive_score":4.0,"rank":29,"score":2.0,"sonneborn_berger":2.5,"tpr":0,"tpr_mixed":0},{"average_rating_cut":1000.0,"buchholz":7.5,"buchholz_cut":4.0,"color_balance":0,"player":29,"progressive_score":7.0,"rank":30,"score":2.0,"sonneborn_berger":2.0,"tpr":0,"tpr_mixed":0},{"average_rating_cut":1000.0,"buchholz":7.5,"buchholz_cut":4.0,"color_balance":0,"player":26,"progressive_score":5.0,"rank":31,"score":2.0,"sonneborn_berger":1.5,"tpr":0,"tpr_mixed":0},{"average_rating_cut":1000.0,"buchholz":7.0,"buchholz_cut":3.0,"color_balance":0,"player":34,"progressive_score":5.0,"rank":32,"score":2.0,"sonneborn_berger":2.5,"tpr":0,"tpr_mixed":0},{"average_rating_cut":1000.0,"buchholz":6.5,"buchholz_cut":3.0,"color_balance":0,"player":16,"progressive_score":3.0,"rank":33,"score":2.0,"sonneborn_berger":1.5,"tpr":0,"tpr_mixed":0},{"average_rating_cut":1000.0,"buchholz":6.5,"buchholz_cut":3.5,"color_balance":0,"player":9,"progressive_score":5.0,"rank":34,"score":2.0,"sonneborn_berger":1.0,"tpr":0,"tpr_mixed":0},{"average_rating_cut":1000.0,"buchholz":6.0,"buchholz_cut":2.5,"color_balance":0,"player":33,"progressive_score":5.0,"rank":35,"score":2.0,"sonneborn_berger":1.0,"tpr":0,"tpr_mixed":0},{"average_rating_cut":1000.0,"buchholz":5.0,"buchholz_cut":3.0,"color_balance":0,"player":49,"progressive_score":4.0,"rank":36,"score":2.0,"sonneborn_berger":1.0,"tpr":0,"tpr_mixed":0},{"average_rating_cut":1000.0,"buchholz":5.0,"buchholz_cut":2.0,"color_balance":0,"player":53,"progressive_score":5.0,"rank":37,"score":2.0,"sonneborn_berger":0.0,"tpr":0,"tpr_mixed":0},{"average_rating_cut":1000.0,"buchholz":7.0,"buchholz_cut":3.5,"color_balance":0,"player":27,"progressive_score":3.5,"rank":38,"score":1.5,"sonneborn_berger":1.25,"tpr":0,"tpr_mixed":0},{"average_rating_cut":1000.0,"buchholz":6.5,"buchholz_cut":3.5,"color_balance":0,"player":54,"progressive_score":4.5,"rank":39,"score":1.5,"sonneborn_berger":1.75,"tpr":0,"tpr_mixed":0},{"average_rating_cut":1000.0,"buchholz":10.0,"buchholz_cut":5.0,"color_balance":0,"player":5,"progressive_score":4.0,"rank":40,"score":1.0,"sonneborn_berger":2.0,"tpr":0,"tpr_mixed":0},{"average_rating_cut":1000.0,"buchholz":8.5,"buchholz_cut":4.5,"color_balance":2,"player":6,"progressive_score":3.0,"rank":41,"score":1.0,"sonneborn_berger":1.0,"tpr":0,"tpr_mixed":0},{"average_rating_cut":1000.0,"buchholz":8.5,"buchholz_cut":4.5,"color_balance":2,"player":57,"progressive_score":4.0,"rank":42,"score":1.0,"sonneborn_berger":1.0,"tpr":0,"tpr_mixed":0},{"average_rating_cut":1000.0,"buchholz":8.0,"buchholz_cut":4.5,"color_balance":2,"player":3,"progressive_score":4.0,"rank":43,"score":1.0,"sonneborn_berger":0.0,"tpr":0,"tpr_mixed":0},{"average_rating_cut":1000.0,"buchholz":8.0,"buchholz_cut":5.0,"color_balance":0,"player":23,"progressive_score":1.0,"rank":44,"score":1.0,"sonneborn_berger":0.0,"tpr":0,"tpr_mixed":0},{"average_rating_cut":1000.0,"buchholz":8.0,"buchholz_cut":4.5,"color_balance":0,"player":41,"progressive_score":1.0,"rank":45,"score":1.0,"sonneborn_berger":0.0,"tpr":0,"tpr_mixed":0},{"average_rating_cut":1000.0,"buchholz":7.5,"buchholz_cut":4.0,"color_balance":2,"player":30,"progressive_score":3.0,"rank":46,"score":1.0,"sonneborn_berger":1.0,"tpr":0,"tpr_mixed":0},{"average_rating_cut":1000.0,"buchholz":7.5,"buchholz_cut":4.0,"color_balance":0,"player":15,"progressive_score":4.0,"rank":47,"score":1.0,"sonneborn_berger":0.5,"tpr":0,"tpr_mixed":0},{"average_rating_cut":1000.0,"buchholz":7.5,"buchholz_cut":4.5,"color_balance":0,"player":7,"progressive_score":2.0,"rank":48,"score":1.0,"sonneborn_berger":0.0,"tpr":0,"tpr_mixed":0},{"average_rating_cut":1000.0,"buchholz":7.0,"buchholz_cut":4.0,"color_balance":0,"player":58,"progressive_score":3.0,"rank":49,"score":1.0,"sonneborn_berger":1.0,"tpr":0,"tpr_mixed":0},{"average_rating_cut":1000.0,"buchholz":7.0,"buchholz_cut":4.0,"color_balance":0,"player":51,"progressive_score":2.0,"rank":50,"score":1.0,"sonneborn_berger":0.0,"tpr":0,"tpr_mixed":0},{"average_rating_cut":1000.0,"buchholz":6.5,"buchholz_cut":3.5,"color_balance":0,"player":25,"progressive_score":2.0,"rank":51,"score":1.0,"sonneborn_berger":0.5,"tpr":0,"tpr_mixed":0},{"average_rating_cut":1000.0,"buchholz":6.5,"buchholz_cut":4.0,"color_balance":0,"player":28,"progressive_score":2.0,"rank":52,"score":1.0,"sonneborn_berger":0.5,"tpr":0,"tpr_mixed":0},{"average_rating_cut":1000.0,"buchholz":6.5,"buchholz_cut":4.0,"color_balance":0,"player":37,"progressive_score":4.0,"rank":53,"score":1.0,"sonneborn_berger":0.5,"tpr":0,"tpr_mixed":0},{"average_rating_cut":1000.0,"buchholz":5.5,"buchholz_cut":3.0,"color_balance":0,"player":44,"progressive_score":2.0,"rank":54,"score":1.0,"sonneborn_berger":0.5,"tpr":0,"tpr_mixed":0},{"average_rating_cut":1000.0,"buchholz":7.5,"buchholz_cut":3.5,"color_balance":2,"player":10,"progressive_score":0.0,"rank":55,"score":0.0,"sonneborn_berger":0.0,"tpr":0,"tpr_mixed":0},{"average_rating_cut":1000.0,"buchholz":6.5,"buchholz_cut":3.5,"color_balance":0,"player":32,"progressive_score":0.0,"rank":56,"score":0.0,"sonneborn_berger":0.0,"tpr":0,"tpr_mixed":0},{"average_rating_cut":1000.0,"buchholz":6.0,"buchholz_cut":3.0,"color_balance":0,"player":24,"progressive_score":0.0,"rank":57,"score":0.0,"sonneborn_berger":0.0,"tpr":0,"tpr_mixed":0},{"average_rating_cut":1000.0,"buchholz":5.5,"buchholz_cut":2.5,"color_balance":2,"player":4,"progressive_score":0.0,"rank":58,"score":0.0,"sonneborn_berger":0.0,"tpr":0,"tpr_mixed":0},{"average_rating_cut":1000.0,"buchholz":5.5,"buchholz_cut":2.0,"color_balance":2,"player":8,"progressive_score":0.0,"rank":59,"score":0.0,"sonneborn_berger":0.0,"tpr":0,"tpr_mixed":0}]},{"byes":[{"player":3,"score":0.0},{"player":4,"score":0.0},{"player":5,"score":0.0},{"player":6,"score":0.0},{"player":8,"score":0.0},{"player":10,"score":0.0},{"player":30,"score":0.0},{"pairing_allocated":true,"player":32,"score":1.0},{"player":57,"score":0.0}],"date":"2025-09-13","number":5,"pairings":[{"black":13,"black_points":0.0,"table":1,"white":17,"white_points":1.0},{"black":21,"black_points":1.0,"table":2,"white":12,"white_points":0.0},{"black":43,"black_points":1.0,"table":3,"white":18,"white_points":0.0},{"black":48,"black_points":0.0,"table":4,"white":22,"white_points":1.0},{"black":55,"black_points":0.0,"table":5,"white":35,"white_points":1.0},{"black":36,"black_points":0.0,"table":6,"white":46,"white_points":1.0},{"black":39,"black_points":1.0,"table":7,"white":52,"white_points":0.0},{"black":45,"black_points":0.5,"table":8,"white":59,"white_points":0.5},{"black":31,"black_points":1.0,"table":9,"white":14,"white_points":0.0},{"black":38,"black_points":1.0,"table":10,"white":50,"white_points":0.0},{"black":1,"black_points":1.0,"table":11,"white":34,"white_points":0.0},{"black":29,"black_points":0.0,"table":12,"white":2,"white_points":1.0},{"black":9,"black_points":0.0,"table":13,"white":40,"white_points":1.0},{"black":11,"black_points":1.0,"table":14,"white":49,"white_points":0.0},{"black":33,"black_points":0.0,"table":15,"white":16,"white_points":1.0},{"black":19,"black_points":0.0,"table":16,"white":56,"white_points":1.0},{"black":47,"black_points":0.0,"table":17,"white":20,"white_points":1.0},{"black":53,"black_points":1.0,"table":18,"white":26,"white_points":0.0},{"black":27,"black_points":0.5,"table":19,"white":42,"white_points":0.5},{"black":15,"black_points":1.0,"table":20,"white":54,"white_points":0.0},{"black":7,"black_points":1.0,"table":21,"white":37,"white_points":0.0},{"black":23,"black_points":0.5,"table":22,"white":41,"white_points":0.5},{"black":25,"black_points":0.0,"table":23,"white":44,"white_points":1.0},{"black":51,"black_points":1.0,"table":24,"white":28,"white_points":0.0},{"black":24,"black_points":0.0,"table":25,"white":58,"white_points":1.0}],"ranking":[{"average_rating_cut":1000.0,"buchholz":18.0,"buchholz_cut":11.0,"color_balance":-1,"mutual_result_top":0.0,"player":17,"progressive_score":15.0,"rank":1,"score":5.0,"sonneborn_berger":18.0,"tpr":0,"tpr_mixed":0},{"average_rating_cut":1000.0,"buchholz":15.0,"buchholz_cut":9.0,"color_balance":-1,"mutual_result_top":0.0,"player":21,"progressive_score":15.0,"rank":2,"score":5.0,"sonneborn_berger":15.0,"tpr":0,"tpr_mixed":0},{"average_rating_cut":1000.0,"buchholz":14.0,"buchholz_cut":8.5,"color_balance":-1,"player":43,"progressive_score":13.0,"rank":3,"score":4.5,"sonneborn_berger":12.25,"tpr":0,"tpr_mixed":0},{"average_rating_cut":1000.0,"buchholz":18.0,"buchholz_cut":10.5,"color_balance":-1,"player":13,"progressive_score":14.0,"rank":4,"score":4.0,"sonneborn_berger":13.0,"tpr":0,"tpr_mixed":0},{"average_rating_cut":1000.0,"buchholz":14.5,"buchholz_cut":8.5,"color_balance":1,"player":22,"progressive_score":13.0,"rank":5,"score":4.0,"sonneborn_berger":10.5,"tpr":0,"tpr_mixed":0},{"average_rating_cut":1000.0,"buchholz":14.5,"buchholz_cut":8.0,"color_balance":-1,"player":39,"progressive_score":12.0,"rank":6,"score":4.0,"sonneborn_berger":9.5,"tpr":0,"tpr_mixed":0},{"average_rating_cut":1000.0,"buchholz":14.5,"buchholz_cut":8.0,"color_balance":1,"player":46,"progressive_score":10.0,"rank":7,"score":4.0,"sonneborn_berger":9.5,"tpr":0,"tpr_mixed":0},{"average_rating_cut":1000.0,"buchholz":12.5,"buchholz_cut":7.5,"color_balance":1,"player":35,"progressive_score":11.0,"rank":8,"score":4.0,"sonneborn_berger":9.5,"tpr":0,"tpr_mixed":0},{"average_rating_cut":1000.0,"buchholz":17.0,"buchholz_cut":11.0,"color_balance":1,"player":12,"progressive_score":12.0,"rank":9,"score":3.5,"sonneborn_berger":9.75,"tpr":0,"tpr_mixed":0},{"average_rating_cut":1000.0,"buchholz":16.5,"buchholz_cut":9.5,"color_balance":1,"player":59,"progressive_score":12.5,"rank":10,"score":3.5,"sonneborn_berger":9.75,"tpr":0,"tpr_mixed":0},{"average_rating_cut":1000.0,"buchholz":14.5,"buchholz_cut":9.0,"color_balance":-1,"player":45,"progressive_score":12.5,"rank":11,"score":3.5,"sonneborn_berger":9.5,"tpr":0,"tpr_mixed":0},{"average_rating_cut":1000.0,"buchholz":13.0,"buchholz_cut":7.0,"color_balance":1,"player":38,"progressive_score":11.0,"rank":12,"score":3.5,"sonneborn_berger":7.75,"tpr":0,"tpr_mixed":0},{"average_rating_cut":1000.0,"buchholz":12.0,"buchholz_cut":8.0,"color_balance":-1,"player":31,"progressive_score":8.5,"rank":13,"score":3.5,"sonneborn_berger":7.75,"tpr":0,"tpr_mixed":0},{"average_rating_cut":1000.0,"buchholz":17.0,"buchholz_cut":10.0,"color_balance":-1,"player":36,"progressive_score":12.0,"rank":14,"score":3.0,"sonneborn_berger":8.0,"tpr":0,"tpr_mixed":0},{"average_rating_cut":1000.0,"buchholz":16.0,"buchholz_cut":9.5,"color_balance":1,"player":18,"progressive_score":11.0,"rank":15,"score":3.0,"sonneborn_berger":8.0,"tpr":0,"tpr_mixed":0},{"average_rating_cut":1000.0,"buchholz":15.0,"buchholz_cut":9.0,"color_balance":-1,"player":55,"progressive_score":11.0,"rank":16,"score":3.0,"sonneborn_berger":7.0,"tpr":0,"tpr_mixed":0},{"average_rating_cut":1000.0,"buchholz":15.0,"buchholz_cut":8.0,"color_balance":1,"player":48,"progressive_score":10.0,"rank":17,"score":3.0,"sonneborn_berger":6.0,"tpr":0,"tpr_mixed":0},{"average_rating_cut":1000.0,"buchholz":14.5,"buchholz_cut":7.5,"color_balance":1,"player":56,"progressive_score":10.0,"rank":18,"score":3.0,"sonneborn_berger":6.0,"tpr":0,"tpr_mixed":0},{"average_rating_cut":1000.0,"buchholz":14.5,"buchholz_cut":8.0,"color_balance":1,"player":52,"progressive_score":10.0,"rank":19,"score":3.0,"sonneborn_berger":5.5,"tpr":0,"tpr_mixed":0},{"average_rating_cut":1000.0,"buchholz":14.0,"buchholz_cut":8.0,"color_balance":1,"player":20,"progressive_score":9.0,"rank":20,"score":3.0,"sonneborn_berger":7.0,"tpr":0,"tpr_mixed":0},{"average_rating_cut":1000.0,"buchholz":14.0,"buchholz_cut":8.0,"color_balance":1,"player":40,"progressive_score":9.0,"rank":21,"score":3.0,"sonneborn_berger":7.0,"tpr":0,"tpr_mixed":0},{"average_rating_cut":1000.0,"buchholz":14.0,"buchholz_cut":8.5,"color_balance":1,"player":2,"progressive_score":10.0,"rank":22,"score":3.0,"sonneborn_berger":6.5,"tpr":0,"tpr_mixed":0},{"average_rating_cut":1000.0,"buchholz":13.0,"buchholz_cut":7.5,"color_balance":-1,"player":11,"progressive_score":7.0,"rank":23,"score":3.0,"sonneborn_berger":6.0,"tpr":0,"tpr_mixed":0},{"average_rating_cut":1000.0,"buchholz":12.0,"buchholz_cut":7.5,"color_balance":-1,"player":1,"progressive_score":8.0,"rank":24,"score":3.0,"sonneborn_berger":5.5,"tpr":0,"tpr_mixed":0},{"average_rating_cut":1000.0,"buchholz":10.5,"buchholz_cut":6.0,"color_balance":1,"player":16,"progressive_score":6.0,"rank":25,"score":3.0,"sonneborn_berger":5.0,"tpr":0,"tpr_mixed":0},{"average_rating_cut":1000.0,"buchholz":8.5,"buchholz_cut":5.5,"color_balance":-1,"player":53,"progressive_score":8.0,"rank":26,"score":3.0,"sonneborn_berger":2.5,"tpr":0,"tpr_mixed":0},{"average_rating_cut":1000.0,"buchholz":15.0,"buchholz_cut":9.0,"color_balance":1,"player":50,"progressive_score":7.5,"rank":27,"score":2.5,"sonneborn_berger":4.75,"tpr":0,"tpr_mixed":0},{"average_rating_cut":1000.0,"buchholz":14.5,"buchholz_cut":9.0,"color_balance":1,"player":14,"progressive_score":8.0,"rank":28,"score":2.5,"sonneborn_berger":4.75,"tpr":0,"tpr_mixed":0},{"average_rating_cut":1000.0,"buchholz":12.5,"buchholz_cut":7.0,"color_balance":1,"player":42,"progressive_score":5.5,"rank":29,"score":2.5,"sonneborn_berger":4.5,"tpr":0,"tpr_mixed":0},{"average_rating_cut":1000.0,"buchholz":13.5,"buchholz_cut":8.0,"color_balance":-1,"player":19,"progressive_score":7.0,"rank":30,"score":2.0,"sonneborn_berger":3.5,"tpr":0,"tpr_mixed":0},{"average_rating_cut":1000.0,"buchholz":12.5,"buchholz_cut":8.5,"color_balance":-1,"player":47,"progressive_score":6.0,"rank":31,"score":2.0,"sonneborn_berger":4.0,"tpr":0,"tpr_mixed":0},{"average_rating_cut":1000.0,"buchholz":12.5,"buchholz_cut":8.0,"color_balance":1,"player":26,"progressive_score":7.0,"rank":32,"score":2.0,"sonneborn_berger":3.5,"tpr":0,"tpr_mixed":0},{"average_rating_cut":1000.0,"buchholz":12.0,"buchholz_cut":7.0,"color_balance":-1,"player":15,"progressive_score":6.0,"rank":33,"score":2.0,"sonneborn_berger":3.0,"tpr":0,"tpr_mixed":0},{"average_rating_cut":1000.0,"buchholz":12.0,"buchholz_cut":7.5,"color_balance":-1,"player":29,"progressive_score":9.0,"rank":34,"score":2.0,"sonneborn_berger":3.0,"tpr":0,"tpr_mixed":0},{"average_rating_cut":1000.0,"buchholz":12.0,"buchholz_cut":7.5,"color_balance":-1,"player":9,"progressive_score":7.0,"rank":35,"score":2.0,"sonneborn_berger":1.5,"tpr":0,"tpr_mixed":0},{"average_rating_cut":1000.0,"buchholz":11.5,"buchholz_cut":7.5,"color_balance":-1,"player":33,"progressive_score":7.0,"rank":36,"score":2.0,"sonneborn_berger":2.5,"tpr":0,"tpr_mixed":0},{"average_rating_cut":1000.0,"buchholz":11.0,"buchholz_cut":7.0,"color_balance":-1,"player":27,"progressive_score":5.5,"rank":37,"score":2.0,"sonneborn_berger":3.0,"tpr":0,"tpr_mixed":0},{"average_rating_cut":1000.0,"buchholz":11.0,"buchholz_cut":6.5,"color_balance":1,"player":34,"progressive_score":7.0,"rank":38,"score":2.0,"sonneborn_berger":3.0,"tpr":0,"tpr_mixed":0},{"average_rating_cut":1000.0,"buchholz":10.0,"buchholz_cut":6.0,"color_balance":-1,"player":51,"progressive_score":4.0,"rank":39,"score":2.0,"sonneborn_berger":1.0,"tpr":0,"tpr_mixed":0},{"average_rating_cut":1000.0,"buchholz":9.5,"buchholz_cut":6.0,"color_balance":-1,"player":7,"progressive_score":4.0,"rank":40,"score":2.0,"sonneborn_berger":1.5,"tpr":0,"tpr_mixed":0},{"average_rating_cut":1000.0,"buchholz":9.0,"buchholz_cut":5.0,"color_balance":1,"player":44,"progressive_score":4.0,"rank":41,"score":2.0,"sonneborn_berger":2.0,"tpr":0,"tpr_mixed":0},{"average_rating_cut":1000.0,"buchholz":9.0,"buchholz_cut":6.0,"color_balance":1,"player":49,"progressive_score":6.0,"rank":42,"score":2.0,"sonneborn_berger":1.0,"tpr":0,"tpr_mixed":0},{"average_rating_cut":1000.0,"buchholz":7.5,"buchholz_cut":5.5,"color_balance":1,"player":58,"progressive_score":5.0,"rank":43,"score":2.0,"sonneborn_berger":1.5,"tpr":0,"tpr_mixed":0},{"average_rating_cut":1000.0,"buchholz":11.0,"buchholz_cut":7.0,"color_balance":1,"player":41,"progressive_score":2.5,"rank":44,"score":1.5,"sonneborn_berger":1.25,"tpr":0,"tpr_mixed":0},{"average_rating_cut":1000.0,"buchholz":10.5,"buchholz_cut":6.5,"color_balance":-1,"player":23,"progressive_score":2.5,"rank":45,"score":1.5,"sonneborn_berger":0.5,"tpr":0,"tpr_mixed":0},{"average_rating_cut":1000.0,"buchholz":9.0,"buchholz_cut":6.0,"color_balance":1,"player":54,"progressive_score":6.0,"rank":46,"score":1.5,"sonneborn_berger":2.0,"tpr":0,"tpr_mixed":0},{"average_rating_cut":1000.0,"buchholz":14.5,"buchholz_cut":8.5,"color_balance":1,"player":5,"progressive_score":5.0,"rank":47,"score":1.0,"sonneborn_berger":2.0,"tpr":0,"tpr_mixed":0},{"average_rating_cut":1000.0,"buchholz":13.0,"buchholz_cut":8.0,"color_balance":3,"player":3,"progressive_score":5.0,"rank":48,"score":1.0,"sonneborn_berger":0.5,"tpr":0,"tpr_mixed":0},{"average_rating_cut":1000.0,"buchholz":12.5,"buchholz_cut":7.5,"color_balance":3,"player":30,"progressive_score":4.0,"rank":49,"score":1.0,"sonneborn_berger":2.0,"tpr":0,"tpr_mixed":0},{"average_rating_cut":1000.0,"buchholz":12.5,"buchholz_cut":7.5,"color_balance":3,"player":6,"progressive_score":4.0,"rank":50,"score":1.0,"sonneborn_berger":1.0,"tpr":0,"tpr_mixed":0},{"average_rating_cut":1000.0,"buchholz":12.5,"buchholz_cut":7.5,"color_balance":3,"player":57,"progressive_score":5.0,"rank":51,"score":1.0,"sonneborn_berger":1.0,"tpr":0,"tpr_mixed":0},{"average_rating_cut":1000.0,"buchholz":11.0,"buchholz_cut":7.0,"color_balance":1,"player":37,"progressive_score":5.0,"rank":52,"score":1.0,"sonneborn_berger":1.0,"tpr":0,"tpr_mixed":0},{"average_rating_cut":1000.0,"buchholz":10.0,"buchholz_cut":6.5,"color_balance":1,"player":28,"progressive_score":3.0,"rank":53,"score":1.0,"sonneborn_berger":1.0,"tpr":0,"tpr_mixed":0},{"average_rating_cut":1000.0,"buchholz":9.0,"buchholz_cut":6.0,"color_balance":1,"player":32,"progressive_score":1.0,"rank":54,"score":1.0,"sonneborn_berger":0.0,"tpr":0,"tpr_mixed":0},{"average_rating_cut":1000.0,"buchholz":8.5,"buchholz_cut":5.0,"color_balance":-1,"player":25,"progressive_score":3.0,"rank":55,"score":1.0,"sonneborn_berger":1.0,"tpr":0,"tpr_mixed":0},{"average_rating_cut":1000.0,"buchholz":10.5,"buchholz_cut":5.5,"color_balance":3,"player":10,"progressive_score":0.0,"rank":56,"score":0.0,"sonneborn_berger":0.0,"tpr":0,"tpr_mixed":0},{"average_rating_cut":1000.0,"buchholz":10.0,"buchholz_cut":5.5,"color_balance":-1,"player":24,"progressive_score":0.0,"rank":57,"score":0.0,"sonneborn_berger":0.0,"tpr":0,"tpr_mixed":0},{"average_rating_cut":1000.0,"buchholz":8.0,"buchholz_cut":3.5,"color_balance":3,"player":8,"progressive_score":0.0,"rank":58,"score":0.0,"sonneborn_berger":0.0,"tpr":0,"tpr_mixed":0},{"average_rating_cut":1000.0,"buchholz":7.5,"buchholz_cut":4.5,"color_balance":3,"player":4,"progressive_score":0.0,"rank":59,"score":0.0,"sonneborn_berger":0.0,"tpr":0,"tpr_mixed":0}]}],"tiebreaks":["score","mutual_result_top","buchholz","sonneborn_berger","alphabetic"],"updated_at":"2025-09-14T13:39:06Z"}